{
  "internal_control_id": "CMS-02",
  "internal_control_name": "Customer Authentication",
  "processed_at": "2026-03-20T10:17:36.281028+00:00",
  "total_mapped": 2,
  "mappings": [
    {
      "safeguard_id": "6.3",
      "framework": "CIS Controls v8.1",
      "mapping": "FULL",
      "reason": "Requiring MFA for externally-exposed applications directly implements secure log-on procedures for customer-facing applications, satisfying the primary security objective of CMS-02."
    },
    {
      "safeguard_id": "5.2",
      "framework": "CIS Controls v8.1",
      "mapping": "PARTIAL",
      "reason": "Using unique and strong passwords for all enterprise assets addresses the credential strength component of secure log-on procedures, supporting the security objective but not covering the full scope of external application authentication mechanisms like MFA."
    }
  ]
}